nonebot/adapters/dodo/__init__.py
nonebot/adapters/dodo/adapter.py
nonebot/adapters/dodo/bot.py
nonebot/adapters/dodo/compat.py
nonebot/adapters/dodo/config.py
nonebot/adapters/dodo/event.py
nonebot/adapters/dodo/exception.py
nonebot/adapters/dodo/message.py
nonebot/adapters/dodo/models.py
nonebot/adapters/dodo/utils.py
nonebot_adapter_dodo-0.2.1.dist-info/LICENSE
nonebot_adapter_dodo-0.2.1.dist-info/METADATA
nonebot_adapter_dodo-0.2.1.dist-info/WHEEL
nonebot_adapter_dodo-0.2.1.dist-info/RECORD
