Metadata-Version: 2.1
Name: nonebot-adapter-dodo
Version: 0.2.1
Summary: Dodo adapter for nonebot2
Home-page: https://github.com/nonebot/adapter-dodo
License: MIT
Keywords: nonebot,dodo,bot
Author: CMHopeSunshine
Author-email: 277073121@qq.com
Requires-Python: >=3.8,<4.0
Classifier: License :: OSI Approved :: MIT License
Classifier: Programming Language :: Python :: 3
Classifier: Programming Language :: Python :: 3.8
Classifier: Programming Language :: Python :: 3.9
Classifier: Programming Language :: Python :: 3.10
Classifier: Programming Language :: Python :: 3.11
Classifier: Programming Language :: Python :: 3.12
Requires-Dist: nonebot2 (>=2.2.1,<3.0.0)
Project-URL: Documentation, https://github.com/nonebot/adapter-dodo
Project-URL: Repository, https://github.com/nonebot/adapter-dodo
